{
  "project_name": "experiments-fair",
  "tasks": [
    "arc_easy",
    "cola",
    "rte",
    "sst",
    "boolq",
    "copa",
    "wic",
    "multirc",
    "openbookqa",
    "anli_r1",
    "lambada_cloze",
    "wsc",
    "triviaqa",
    "race",
    "webqs",
    "piqa",
    "squad2"
  ],
  "n_shots": [
    0,
    32,
    128,
    512,
    2048
  ],
  "results_dir": "where the results will be saved - /home/olab/kirstain/lm-evaluation-harness/results_arzi",
  "temp_dir": "directory to keep temporary checkpoints during the run - /home/olab/kirstain/lm-evaluation-harness/tmp/"
}